Metadata-Version: 2.1
Name: docbrown
Version: 0.5.0
Summary: an empirical progress library
Home-page: https://github.com/kmohrf/docbrown
Author: Konrad Mohrfeldt
Author-email: konrad.mohrfeldt@farbdev.org
License: GPLv3+
Platform: UNKNOWN
Classifier: Development Status :: 4 - Beta
Classifier: License :: OSI Approved :: GNU General Public License v3 or later (GPLv3+)
Classifier: Programming Language :: Python :: 3 :: Only
